{
  "adminClosedComment": false,
  "annotationAction": null,
  "answerType": "normal",
  "attachedInfo": "ogEQCAQQAxiPxeHzBSD8yqaDAZICJQoJMzE4MjQ2MDUxEgoxNTg0OTQ3ODU1GAQiCklNQUdFX1RFWFQ=",
  "author": {
    "avatarUrl": "https://pic1.zhimg.com/v2-e47b374c3d54b1967ad7cd5705fe54f2_l.jpg?source=1940ef5c",
    "avatarUrlTemplate": "https://picx.zhimg.com/v2-e47b374c3d54b1967ad7cd5705fe54f2.jpg?source=1940ef5c",
    "badge": [],
    "badgeV2": {
      "detailBadges": [],
      "icon": "",
      "mergedBadges": [],
      "nightIcon": "",
      "title": ""
    },
    "exposedMedal": {
      "avatarUrl": "",
      "description": "",
      "medalId": "0",
      "medalName": ""
    },
    "followerCount": 0,
    "gender": -1,
    "headline": "",
    "id": "d2eae1dddb75913e5cf38703880166df",
    "isAdvertiser": false,
    "isFollowed": false,
    "isFollowing": false,
    "isOrg": false,
    "isPrivacy": false,
    "name": "锟斤拷",
    "type": "people",
    "url": "https://www.zhihu.com/api/v4/people/d2eae1dddb75913e5cf38703880166df",
    "urlToken": "kun-jin-kao-75",
    "userType": "people"
  },
  "canComment": {
    "reason": "",
    "status": true
  },
  "collapseReason": "",
  "collapsedBy": "nobody",
  "commentCount": 0,
  "commentPermission": "censor",
  "content": "<p data-pid=\"_XFC6t1D\">小号来答。有人可能觉得开小号像骗子可私我告诉你我大号，没答过什么题但玩知乎已经几年了，用小号主要是不想被熟人看见然后说三道四</p><p data-pid=\"wEPNCfig\">以下正题</p><p data-pid=\"ueFbqlYO\">98年男，身高174体重70kg疫情期间还可能涨了比较胖，脸也不好看，介意的就不用聊了</p><p data-pid=\"aC2j0MhF\">北京土著独生子，家庭条件算差的了，并不能V你50（</p><p data-pid=\"xPz9c9fP\">211大学本科，央企程序员已工作三年，目前月到手10k</p><p data-pid=\"z6Er7kXl\">家里很开明，就算是我不结婚或者不要孩子都尊重我的决定，所以也没什么压力。相信如果有了另一半那婆媳关系之类的也肯定不会有问题</p><p data-pid=\"TZGiNX3O\">比较直不太会和女生聊天，只在高中谈过一次恋爱，要不然也不会之后一直单身至此</p><p data-pid=\"SalCUvQU\">比较宅，爱好也都是搞技术之类的不出门不运动那种</p><p data-pid=\"1A30T6Jw\">至于对另一半的要求，最重要的还是合得来吧，外貌什么的不重要毕竟我自己也就那样，写写一些我认为比较重要的</p><p data-pid=\"ShWB2JZD\">最好是正在或打算在北京发展的，当然不绝对，如果聊得来也可考虑异地</p><p data-pid=\"mj5wOwhF\">可以不喜欢我爱好的东西，至少不能反感吧，要不然双方都痛苦</p><p data-pid=\"jF0djrpo\">绝对不接受抽烟喝酒的</p><p data-pid=\"hVmjijQ1\">不管有多少前任，务必断的彻底。曾经被恶心到过，所以养鱼的也千万别来</p><p data-pid=\"59QnQLHo\">家庭条件无所谓，绝对不要有比较封建的什么重男轻女，天价彩礼，婚闹之类的就行</p><p data-pid=\"ndQqAHcS\">个人还是比较信奉门当户对的，家庭条件差不多就好，能两个人一起过日子就行了</p><p data-pid=\"WkedqCIC\">我呢，也就是一普通人，也只想找个普通女孩子过一辈子，看了知乎遍地精英只能说差太远了注孤生了</p><p data-pid=\"rh8ReWI1\">想聊聊的可以直接评论/私聊，评论开筛选了</p>",
  "contentMark": {},
  "createdTime": 1605840334,
  "decorativeLabels": [],
  "editableContent": "",
  "excerpt": "小号来答。有人可能觉得开小号像骗子可私我告诉你我大号，没答过什么题但玩知乎已经几年了，用小号主要是不想被熟人看见然后说三道四 以下正题 98年男，身高174体重70kg疫情期间还可能涨了比较胖，脸也不好看，介意的就不用聊了 北京土著独生子，家庭条件算差的了，并不能V你50（ 211大学本科，央企程序员已工作三年，目前月到手10k 家里很开明，就算是我不结婚或者不要孩子都尊重我的决定，所以也没什么压力。相信如果有了另一…",
  "extras": "",
  "id": 1584947855,
  "isCollapsed": false,
  "isCopyable": false,
  "isLabeled": false,
  "isMine": false,
  "isNormal": true,
  "isSticky": false,
  "isVisible": true,
  "markInfos": [],
  "question": {
    "created": 1525054468,
    "id": 275359100,
    "questionType": "normal",
    "relationship": {},
    "title": "你的择偶标准是怎样的？",
    "type": "question",
    "updatedTime": 1593436149,
    "url": "https://www.zhihu.com/api/v4/questions/275359100"
  },
  "reactionInstruction": {},
  "relationship": {
    "isAuthor": false,
    "isAuthorized": false,
    "isNothelp": false,
    "isThanked": false,
    "upvotedFollowees": [],
    "voting": 0
  },
  "relevantInfo": {
    "isRelevant": false,
    "relevantText": "",
    "relevantType": ""
  },
  "reshipmentSettings": "disallowed",
  "rewardInfo": {
    "canOpenReward": false,
    "isRewardable": false,
    "rewardMemberCount": 0,
    "rewardTotalMoney": 0,
    "tagline": ""
  },
  "settings": {
    "tableOfContents": {
      "enabled": false
    }
  },
  "stickyInfo": "",
  "suggestEdit": {
    "reason": "",
    "status": false,
    "tip": "",
    "title": "",
    "unnormalDetails": {
      "description": "",
      "note": "",
      "reason": "",
      "reasonId": 0,
      "status": ""
    },
    "url": ""
  },
  "thanksCount": 1,
  "thumbnailInfo": {
    "count": 0,
    "thumbnails": [],
    "type": "thumbnail_info"
  },
  "type": "answer",
  "updatedTime": 1688095603,
  "url": "https://www.zhihu.com/api/v4/answers/1584947855",
  "visibleOnlyToAuthor": false,
  "voteupCount": 1,
  "zhiPlusExtraInfo": ""
}
